markups/__init__.py
markups/abstract.py
markups/asciidoc.py
markups/common.py
markups/markdown.py
markups/py.typed
markups/restructuredtext.py
markups/textile.py
markups-4.1.1.dist-info/licenses/LICENSE
markups-4.1.1.dist-info/METADATA
markups-4.1.1.dist-info/WHEEL
markups-4.1.1.dist-info/entry_points.txt
markups-4.1.1.dist-info/top_level.txt
markups-4.1.1.dist-info/RECORD
