Metadata-Version: 2.4
Name: Markups
Version: 4.1.1
Summary: A wrapper around various text markups
Author-email: Dmitry Shachnev <mitya57@gmail.com>
License-Expression: BSD-3-Clause
Project-URL: Homepage, https://github.com/retext-project/pymarkups
Project-URL: Documentation, https://pymarkups.readthedocs.io/en/latest/
Project-URL: Issue Tracker, https://github.com/retext-project/pymarkups/issues/
Project-URL: Changelog, https://pymarkups.readthedocs.io/en/latest/changelog.html
Classifier: Development Status :: 5 - Production/Stable
Classifier: Operating System :: OS Independent
Classifier: Programming Language :: Python
Classifier: Programming Language :: Python :: 3
Classifier: Programming Language :: Python :: 3.10
Classifier: Programming Language :: Python :: 3.11
Classifier: Programming Language :: Python :: 3.12
Classifier: Programming Language :: Python :: 3.13
Classifier: Programming Language :: Python :: 3 :: Only
Classifier: Topic :: Text Processing :: Markup
Classifier: Topic :: Text Processing :: General
Classifier: Topic :: Software Development :: Libraries :: Python Modules
Requires-Python: >=3.10
License-File: LICENSE
Provides-Extra: markdown
Requires-Dist: Markdown>=3; extra == "markdown"
Requires-Dist: PyYAML; extra == "markdown"
Requires-Dist: python-markdown-math; extra == "markdown"
Provides-Extra: restructuredtext
Requires-Dist: docutils; extra == "restructuredtext"
Provides-Extra: textile
Requires-Dist: textile; extra == "textile"
Provides-Extra: highlighting
Requires-Dist: Pygments; extra == "highlighting"
Provides-Extra: asciidoc
Requires-Dist: asciidoc; extra == "asciidoc"
Requires-Dist: lxml; extra == "asciidoc"
Dynamic: license-file
